{
    "system": {
        "errorTitle": "💀 Alert",
        "accessDenied": "🔒 This floor is currently controlled by {ownerName}.",
        "permissionDeniedManageMessages": "⛔ You need the Manage Messages permission.",
        "permissionDeniedAdminDropped": "🛡️ Only Staff can remove claims.",
        "kickPanelTitle": "⚔️ Floor Management",
        "kickPanelPlaceholder": "Select a player to remove...",
        "kickCurrentLabel": "👑 Current Owner:",
        "kickNoClaims": "📭 No active claims found.",
        "kickSuccess": "✅ Claim removed successfully.",
        "kickDMNotice": "⚠️ Your claim on {title} has been removed by Staff.",
        "resetMenuTitle": "🔄 **Select a panel to reset:**",
        "resetMenuPlaceholder": "Choose a panel...",
        "resetNoPanels": "📭 No panels found.",
        "resetPanelNotFound": "❌ Panel `{key}` not found.",
        "resetPanelSuccess": "✅ Panel `{key}` data reset successfully!",
        "resetLogsSuccess": "✅ **{count}** log(s) cleared successfully.",
        "resetLogsConfirm": "⚠️ Are you sure you want to clear **{count}** log(s)?",
        "resetLogsCancel": "❌ Reset cancelled.",
        "resetLogsEmpty": "📭 No logs to clear.",
        "resetLogsDenied": "🛡️ Only Staff can reset logs.",
        "updateRunningGit": "🔄 Running `git pull`...",
        "updateSuccess": "✅ `git pull` completed:\n```\n{output}\n```\n🔄 Restarting...",
        "updateError": "❌ Update error:\n```\n{error}\n```"
    },
    "buttons": {
        "claimLabel": "⚔️ Claim",
        "cancelLabel": "🚪 Leave",
        "nextLabel": "⏭️ Join Queue"
    },
    "cooldowns": {
        "activeTimeout": "⏳ Cooldown active! Try again in {minutes}m {seconds}s.",
        "canceledClaimFeedback": "❌ Claim canceled. A 5-minute cooldown has been applied.",
        "floorReservedNotice": "❌ This floor is temporarily reserved for **{userName}**{timeRemaining}. Please wait for their grace period to expire.",
        "timeRemaining": " (Approximately **{minutes} min** remaining)"
    },
    "tickets": [
        {
            "label": "🎫 1 Ticket • 30min",
            "value": "1"
        },
        {
            "label": "🎫🎫 2 Tickets • 60min",
            "value": "2"
        },
        {
            "label": "🎫🎫🎫 3 Tickets • 90min",
            "value": "3"
        }
    ],
    "rooms": {
        "statusOverview": "🏰 Floor Status",
        "claimBefore": "⌛ Claim before: **{endLimit}**",
        "expectedAt": "🕒 ETA: **{formattedTime}** {timezone}",
        "roomIsOpen": "🟢 Floor is now free to claim.",
        "eventEnded": "🔴 Event window has ended.",
        "nextOpeningTitle": "⏰ Next Respawn",
        "deathTimerRunning": "⏳ Boss already marked as killed. Respawn timer is running.",
        "deathLogged": "💀 Boss kill registered. Respawn timer started.",
        "limitReached": "🚫 You already have an active claim elsewhere.",
        "floorClaimSuccess": "🏆 Floor claimed successfully!",
        "queueJoinedSuccess": "🟨 You joined the queue.",
        "alreadyOwner": "👑 You already control this floor.",
        "alreadyInQueue": "⏳ You're already in the queue.",
        "floorReleasedSuccess": "🔓 Floor released successfully.",
        "removedFromQueueFeedback": "🚪 You left the queue.",
        "actionsCanceledFeedback": "✅ All active claims and reservations have been canceled.",
        "noActiveClaimsFeedback": "❌ You don't have any active claims or queue positions.",
        "antidemonMenuSelectClaim": "👹 Select an Antidemon room:",
        "antidemonMenuSelectNext": "⚔️ Select an Antidemon queue:",
        "antidemonSelectPlaceholder": "Choose a room...",
        "antidemonPromptSelection": "🎫 How many tickets do you want to use?",
        "antidemonTicketPlaceholder": "Choose a duration...",
        "antidemonClaimSuccessEphemeral": "🏆 Antidemon room secured!",
        "antidemonQueueSuccessEphemeral": "🟨 You joined the Antidemon queue.",
        "antidemonQueueLocked": "🔒 This slot is already taken.",
        "antidemonTimeoutCache": "⌛ Selection expired. Try again.",
        "antidemonRoomLeft": "Claim the left room individually",
        "antidemonRoomMid": "Claim the middle room individually",
        "antidemonRoomRight": "Claim the right room individually",
        "antidemonRoomMidLeft": "Claim both middle and left rooms",
        "antidemonRoomMidRight": "Claim both middle and right rooms",
        "antidemonQueueLeft": "Join the queue for the left room",
        "antidemonQueueMid": "Join the queue for the middle room",
        "antidemonQueueRight": "Join the queue for the right room",
        "antidemonQueueMidLeft": "Join queue for both middle and left",
        "antidemonQueueMidRight": "Join queue for both middle and right",
        "summonMenuSelectClaim": "🌀 Select a Summon Location to claim:",
        "summonMenuSelectNext": "🌀 Select a Summon Location to queue:",
        "summonSelectPlaceholder": "Choose a location...",
        "summonClaimSuccessEphemeral": "🏆 Summon location claimed successfully!",
        "summonQueueSuccessEphemeral": "🟨 You joined the queue for this summon location.",
        "dmClaimStartedNotice": "👑 **Claim Active**\n\nYou now control **{title}**.\n⏳ Duration: **{window}**.",
        "dmQueueJoinedNotice": "🟨 **Queue Joined**\n\nYou're now in line for **{title}**.",
        "dmRemovedNotice": "⚠️ **Claim Removed**\n\nYour claim/queue position in **{title}** has ended.\nReason: *{reason}*",
        "floorExpiredDM": "⌛ **Claim Expired**\n\nYour time on **{title}** has ended.",
        "floorTurnArrivedDM": "🟢 **Your Turn!**\n\n**{title}** is now available.\nClaim it within **5 minutes** or lose your spot.",
        "floorAbsenceDM": "❌ **Queue Lost**\n\nYou didn't claim **{title}** in time and lost your position.",
        "antidemonTurnArrivedDM": "🟢 **Your Turn!**\n\nThe Antidemon room **{roomKey}** in **{title}** is ready.\nActivate your tickets within **5 minutes**.",
        "antidemonAbsenceDM": "❌ **Queue Lost**\n\nYou didn't activate your tickets for **{roomKey}** in time.",
        "dmBossNotMarkedWarning": "⚠️ **Boss Reminder**\n\n**{boss}** in **{title}** has been available for over 5 minutes.\nDon't forget to register the kill.",
        "dmImmediateSpawn": "🚨 **INSTANT SPAWN**\n\n**{boss}** has just spawned on **{title}**!",
        "dmImmediateSpawnFixed": "🚨 **INSTANT SPAWN**\n\n**{boss}** has just spawned on **{title}**! Move now!"
    },
    "render": {
        "unknownUser": "Unknown User",
        "joinedAsNext": "Joined as Next",
        "windowPrefix": "Window",
        "joinedNextLine": "Joined next line",
        "memberLabel": "Member",
        "countdownUntil": "until"
    },
    "logs": {
        "title": "📜 DAILY CLAIM REPORT • {date}",
        "noActivity": "No activity recorded today.",
        "autoClose": "Event window closed automatically.",
        "timeout": "Ticket duration expired.",
        "absenceQueue": "Queue lost due to inactivity.",
        "adminRemove": "Removed by Staff.",
        "staffCancel": "Canceled by Staff.",
        "staffQueueCancel": "Queue canceled by Staff.",
        "userCancel": "Claim canceled.",
        "userQueueCancel": "Queue abandoned.",
        "voluntaryLeave": "Floor released.",
        "queueLeave": "Left the queue.",
        "dispatchSuccess": "✅ Report sent successfully.",
        "dispatchError": "❌ Failed to send report.",
        "setupSuccess": "✅ Report channel configured.",
        "setupError": "❌ You don't have permission to configure report channels.",
        "modRequired": "❌ Only Staff can send reports manually.",
        "noChannel": "❌ No report channel configured. Use `!setlogs` first."
    }
}
